collective.taskqueue-1.0-py2.7-nspkg.pth
collective/taskqueue/__init__.py
collective/taskqueue/component.xml
collective/taskqueue/config.py
collective/taskqueue/configure.zcml
collective/taskqueue/datatypes.py
collective/taskqueue/handlers.py
collective/taskqueue/interfaces.py
collective/taskqueue/redisqueue.py
collective/taskqueue/server.py
collective/taskqueue/taskqueue.py
collective/taskqueue/testing.py
collective/taskqueue/pasplugin/__init__.py
collective/taskqueue/pasplugin/configure.zcml
collective/taskqueue/pasplugin/taskauthplugin.py
collective/taskqueue/pasplugin/taskauthplugin.zpt
collective/taskqueue/pasplugin/profiles/default/collective.taskqueue.taskauth.txt
collective/taskqueue/pasplugin/profiles/default/metadata.xml
collective/taskqueue/tests/__init__.py
collective/taskqueue/tests/test_acceptance.py
collective/taskqueue/tests/test_acceptance.robot
collective/taskqueue/tests/test_acceptance.zcml
collective/taskqueue/tests/test_redisqueue.py
collective/taskqueue/tests/test_task_id.py
collective/taskqueue/tests/test_taskqueue.py
collective.taskqueue-1.0.dist-info/METADATA
collective.taskqueue-1.0.dist-info/WHEEL
collective.taskqueue-1.0.dist-info/entry_points.txt
collective.taskqueue-1.0.dist-info/namespace_packages.txt
collective.taskqueue-1.0.dist-info/top_level.txt
collective.taskqueue-1.0.dist-info/RECORD
