Metadata-Version: 2.1
Name: collective.taskqueue
Version: 1.0
Summary: Asyncore-based asynchronous task queue for Plone
Home-page: https://github.com/collective/collective.taskqueue/
Author: Asko Soukka
Author-email: asko.soukka@iki.fi
License: GPL
Platform: UNKNOWN
Classifier: Development Status :: 4 - Beta
Classifier: Environment :: Web Environment
Classifier: Framework :: Plone
Classifier: Framework :: Plone :: 4.3
Classifier: Framework :: Plone :: 5.0
Classifier: Framework :: Plone :: 5.1
Classifier: Framework :: Plone :: 5.2
Classifier: License :: OSI Approved :: GNU General Public License v2 (GPLv2)
Classifier: Programming Language :: Python
Classifier: Programming Language :: Python :: 2.7
Classifier: Topic :: Internet :: WWW/HTTP
Classifier: Topic :: Internet :: WWW/HTTP :: Dynamic Content
Classifier: Topic :: Software Development :: Libraries :: Python Modules
Requires-Dist: setuptools
Requires-Dist: six
Requires-Dist: Zope2
Requires-Dist: five.globalrequest
Provides-Extra: redis
Requires-Dist: redis (>=2.4.10) ; extra == 'redis'
Requires-Dist: msgpack-python ; extra == 'redis'
Provides-Extra: test
Requires-Dist: plone.app.testing ; extra == 'test'
Requires-Dist: plone.app.robotframework (>=0.7.0rc4) ; extra == 'test'
